ICICONSOLE/BasicCypherCommands.py
ICICONSOLE/Utilities.py
ICICONSOLE/__init__.py
ICICONSOLE/__main__.py
ICICONSOLE/helpCypher.json
ICICONSOLE-0.8.0.dist-info/LICENSE
ICICONSOLE-0.8.0.dist-info/METADATA
ICICONSOLE-0.8.0.dist-info/WHEEL
ICICONSOLE-0.8.0.dist-info/entry_points.txt
ICICONSOLE-0.8.0.dist-info/top_level.txt
ICICONSOLE-0.8.0.dist-info/RECORD
