Metadata-Version: 2.1
Name: ICICONSOLE
Version: 0.8.0
Summary: Command-line Interface tailored to working with Neo4j Knowledge Graph Databses.
Author-email: Sahil Samar <sahilsamar031@gmail.com>
License: GNU GENERAL PUBLIC LICENSE
Project-URL: Homepage, https://github.com/AD1616/ICICONSOLE
Keywords: Tapis,CLI,Agave,HPC,Tapis Pods,TACC,Neo4j
Classifier: License :: OSI Approved :: GNU General Public License (GPL)
Classifier: Programming Language :: Python
Classifier: Programming Language :: Python :: 3
Requires-Python: >=3.10
License-File: LICENSE
Requires-Dist: tapipy
Requires-Dist: py2neo
Requires-Dist: pandas
Requires-Dist: datascroller
Requires-Dist: openai
Provides-Extra: dev
